sarvam/__init__.py
sarvam-0.0.0.dist-info/LICENSE
sarvam-0.0.0.dist-info/METADATA
sarvam-0.0.0.dist-info/WHEEL
sarvam-0.0.0.dist-info/top_level.txt
sarvam-0.0.0.dist-info/RECORD
